yplate/__init__.py
yplate/cli.py
yplate3-1.0.dist-info/METADATA
yplate3-1.0.dist-info/WHEEL
yplate3-1.0.dist-info/entry_points.txt
yplate3-1.0.dist-info/top_level.txt
yplate3-1.0.dist-info/RECORD
