Metadata-Version: 2.4
Name: yplate3
Version: 1.0
Summary: Минималистичный Python web-фреймворк в стиле Django, но проще
Home-page: https://github.com/IGBerko/yplate
Author: Itry
Author-email: support@itrypro.ru
Classifier: Programming Language :: Python :: 3
Classifier: License :: OSI Approved :: MIT License
Classifier: Operating System :: OS Independent
Classifier: Framework :: AsyncIO
Classifier: Environment :: Web Environment
Requires-Python: >=3.8
Dynamic: author
Dynamic: author-email
Dynamic: classifier
Dynamic: description
Dynamic: description-content-type
Dynamic: home-page
Dynamic: requires-python
Dynamic: summary
